{"title":"An Open Letter to Graduate Schools:","markdown":{"yaml":{"eval":false,"include":false},"headingText":"An Open Letter to Graduate Schools:","containsRefs":false,"markdown":"\n\n\nIntresting paradigm. Employers want experience. Graduate schools want grades. Competing interests... But they both ultimately want money. \n\nWhat's the point of education? Portfolio projects or mastery of subject? \n\n\n- Dash dashboards\n- Quarto Websites \n- coding word documents\n- writing r packages to do calculus\n- Quarto Revealjs for presentations (free, animations, speaker timer, speaker notes...)\n- character & chapter summarising in readings\n\n\nWhat about pages like these?: \n- https://www.datacamp.com/tutorial/facets-ggplot-r\n- https://www.datacamp.com/tutorial/tidyverse-tutorial-r \n\n```{r}\nlibrary(tidyverse)\nlibrary(plotly)\n```\n\n\n```{r}\ngg_graph <- ggplot(data = data.frame(x = 0), mapping = aes(x = x))+\n                  stat_function(fun = function(x) 2*x + x)+ \n                  xlim(-10, 10)+\n                  ylim(-6, 6)\n\n```\n\n```{r}\ngg_graph\nggplotly(gg_graph)\n```\n\n\n```{r}\ngg1 <- ggplot(cars, aes(x = speed, y = dist)) +\n  geom_point() +\n  geom_smooth(method = \"lm\", formula = y~x, se = FALSE, size = 2, color = \"orange\",\n  linetype = \"dashed\")\ngg1\n```\n\n```{r}\nggplotly(gg1)\n```\n\n\n\n```{r}\n#| eval: false\n\nfun.1 <- function(x) 2*x + x\n\ndata.frame(fun.1)\n```\n\n```{r}\n\nbob <- function(x) {\n      y <- sin(x)\n      return(y)\n}\n\nx <- seq(0, 20, 1)\n\ndata1 <- data.frame(\n      x = x, \n      y = bob(x)\n)\n\ndata1 %>% head()\n# ggplot(aes(x,y))+ \n#       geom_point()+\n#       geom_smooth(formula = bob(x))\n\n```\n\n\n\n```{r}\nfun.1 <- function(x) 2*x + x\n\np <- ggplot(data.frame(x = 0), aes(x = x))\n\n```\n\n\n```{r}\np + stat_function(fun = fun.1) + xlim(-5,5)\n```\n\n```{r}\np + layer(geom = \"path\",        # Default. Can be omitted.\n          stat = \"function\",\n          fun = fun.1,          # Give function\n          mapping = aes(color = \"fun.1\") # Give a meaningful name to color\n          ) +\n    scale_x_continuous(limits = c(-5,5)) +\n    scale_color_manual(name = \"Function\", values = c(\"blue\"))\n```\n\n```{r}\nfun.2 <- function(x) -1 * x + 10\nfun.3 <- function(x) 3 * x + 2\n```\n\n```{r}\nggplot(data = data.frame(x = 0), mapping = aes(x = x))+ \n    layer(stat = \"function\",\n          fun = fun.1,\n          mapping = aes(color = fun.1)\n          ) +\n    layer(stat = \"function\",\n          fun = fun.2,\n          mapping = aes(color = fun.2)\n          ) +\n    layer(stat = \"function\",\n          fun = fun.3,\n          mapping = aes(color = fun.3)\n          ) \n    # scale_x_continuous(limits = c(-5, 5)) +\n    # scale_color_manual(name = \"Functions\",\n    #                    values = c(\"blue\", \"red\", \"green\"), # Color specification\n    #                    labels = c(\"X^2 + X\", \"-X + 10\", \"3X + 2\"))\n```\n\n\n\n```{r}\nx <- 1:10\ndf <- data.frame(x)\nggplot(df, aes(x))+\n    stat_function(fun=function(x) log(x)/(x-3))\n```\n"},"formats":{"html":{"execute":{"fig-width":7,"fig-height":5,"fig-format":"retina","fig-dpi":96,"df-print":"default","error":false,"eval":false,"cache":null,"freeze":false,"echo":true,"output":true,"warning":true,"include":false,"keep-md":false,"keep-ipynb":false,"ipynb":null,"enabled":null,"daemon":null,"daemon-restart":false,"debug":false,"ipynb-filters":[],"engine":"knitr"},"render":{"keep-tex":false,"keep-source":false,"keep-hidden":false,"prefer-html":false,"output-divs":true,"output-ext":"html","fig-align":"default","fig-pos":null,"fig-env":null,"code-fold":"none","code-overflow":"scroll","code-link":false,"code-line-numbers":false,"code-tools":false,"tbl-colwidths":"auto","merge-includes":true,"latex-auto-mk":true,"latex-auto-install":true,"latex-clean":true,"latex-max-runs":10,"latex-makeindex":"makeindex","latex-makeindex-opts":[],"latex-tlmgr-opts":[],"latex-input-paths":[],"latex-output-dir":null,"link-external-icon":false,"link-external-newwindow":false,"self-contained-math":false,"format-resources":[]},"pandoc":{"standalone":true,"wrap":"none","default-image-extension":"png","to":"html","css":["styles.css"],"toc":true,"output-file":"index.html"},"language":{},"metadata":{"lang":"en","fig-responsive":true,"quarto-version":"1.2.219","theme":"cosmo"},"extensions":{"book":{"multiFile":true}}}}}